nara/__init__.py
nara/extra/__init__.py
nara/extra/async_task/__init__.py
nara/extra/async_task/async_thred_task.py
nara/extra/date_time/__init__.py
nara/extra/date_time/today_time.py
nara/extra/extended_json/__init__.py
nara/extra/extended_json/cache.py
nara/extra/extended_json/load_json.py
nara/extra/extended_json/save.py
nara/extra/extended_json/testing_tools.py
nara/extra/extended_sql/__init__.py
nara/extra/extended_sql/dict.py
nara/extra/extended_sql/list.py
nara/extra/extended_sql/text_store.py
nara/extra/extended_sql/queue/__init__.py
nara/extra/fake/DataGenerator.py
nara/extra/fake/__init__.py
nara/extra/fake/data_generator.py
nara/extra/fake/random_data_generator.py
nara/extra/file_manager/__init__.py
nara/extra/file_manager/clear_pycatch.py
nara/extra/file_manager/display_file_struc.py
nara/extra/prompt/__init__.py
nara/extra/prompt/base.py
nara/extra/prompt/type.py
nara/extra/temp_mail/__init__.py
nara/extra/temp_mail/temp_mail.py
nara/extra/temp_mail/temp_mail_io.py
nara/extra/tools/__init__.py
nara/extra/tools/repeat_forever.py
nara/extra/tools/retry.py
nara/extra/tools/run_multiple.py
nara/extra/tools/time_it.py
nara/llm/__init__.py
nara/llm/_cohere.py
nara/llm/_groq.py
nara/llm/_ollama.py
nara/llm/_openai.py
nara/llm/_openrouter.py
nara/llm/_sambanova.py
nara/llm/_together.py
nara/llm/base.py
nara/llm/check_and_install.py
nara/nara/GenFunc.py
nara/nara/GenTemplate.py
nara/nara/TextClassification.py
nara/nara/init.py
nara/nara/classification/__init__.py
nara/nara/classification/text_classification.py
nara/nara/genration/__init__.py
nara/nara/genration/gen_func.py
nara/nara/genration/gen_template.py
nara/nara/genration/initial.py
nara-0.5.dist-info/LICENSE.txt
nara-0.5.dist-info/METADATA
nara-0.5.dist-info/WHEEL
nara-0.5.dist-info/top_level.txt
nara-0.5.dist-info/RECORD
