Metadata-Version: 2.1
Name: nara
Version: 0.5
Summary: nara provides AI-driven real-time information retrieval,all in one sytanx of diffrent models, chatbot interactions, temporary email creation, random data generation, caching, JSON manipulation, async task handling, and structured threading.
Home-page: https://github.com/subh-sk/Nara
Author: Subhash Kumar, Divyansh Shukla, Yateesh Reddy
Maintainer: Nara Developers
Maintainer-email: naravirtualai@gmail.com
License: MIT
Project-URL: Homepage, https://github.com/subh-sk/Nara
Project-URL: Documentation, https://github.com/subh-sk/Nara/wiki
Project-URL: Download, https://pypi.org/project/nara/#files
Project-URL: Release notes, https://github.com/subh-sk/Nara/releases
Project-URL: Source, https://github.com/subh-sk/Nara
Project-URL: Tracker, https://github.com/subh-sk/Nara/issues
Keywords: nara,ai,template generator,cloud storage,temporary email,SQL utilities,datetime utilities,fake data generation,async tasks,file management,time utilities
Classifier: Development Status :: 5 - Production/Stable
Classifier: Intended Audience :: Education
Classifier: Intended Audience :: Developers
Classifier: Topic :: Software Development :: Libraries :: Python Modules
Classifier: Topic :: Software Development :: Testing
Classifier: Operating System :: Microsoft :: Windows :: Windows 10
Classifier: Operating System :: Microsoft :: Windows :: Windows 11
Classifier: Operating System :: Unix
Classifier: Operating System :: MacOS :: MacOS X
Classifier: License :: OSI Approved :: MIT License
Classifier: Programming Language :: Python :: 3.10
Classifier: Programming Language :: Python :: 3.11
Classifier: Programming Language :: Python :: 3.12
Classifier: Programming Language :: Python :: 3.13
Classifier: Topic :: Scientific/Engineering :: Artificial Intelligence
Classifier: Topic :: Scientific/Engineering :: Image Processing
Classifier: Topic :: Scientific/Engineering :: Visualization
Classifier: Topic :: Software Development
Classifier: Topic :: Software Development :: Quality Assurance
Classifier: Topic :: Software Development :: Code Generators
Classifier: Topic :: Software Development :: Libraries
Classifier: Topic :: Software Development :: Libraries :: Application Frameworks
Classifier: Topic :: Software Development :: Libraries :: Python Modules
Classifier: Topic :: Software Development :: Testing
Requires-Python: >=3.10
License-File: LICENSE.txt
Requires-Dist: rich
Requires-Dist: mailtm
Requires-Dist: groq
Requires-Dist: requests
Requires-Dist: python-dotenv
Requires-Dist: datetime
Requires-Dist: aiohttp
Requires-Dist: beautifulsoup4
Requires-Dist: wheel
Requires-Dist: setuptools
Requires-Dist: Pillow
Requires-Dist: telethon
Requires-Dist: pytz
Requires-Dist: humanfriendly
Requires-Dist: faker
Requires-Dist: python-json-logger
Requires-Dist: pycountry
